vsstubs/__init__.py
vsstubs/__main__.py
vsstubs/_version.py
vsstubs/cli.py
vsstubs/constants.py
vsstubs/func.py
vsstubs/py.typed
vsstubs/stubs.py
vsstubs/template.py
vsstubs/types.py
vsstubs/utils.py
vsstubs/_template/__all__.pyi
vsstubs/_template/_typing.pyi
vsstubs/_template/_wrappers.pyi
vsstubs/_template/constants.pyi
vsstubs/_template/env.pyi
vsstubs/_template/formats.pyi
vsstubs/_template/frames.pyi
vsstubs/_template/logging.pyi
vsstubs/_template/misc.pyi
vsstubs/_template/nodes.pyi
vsstubs/_template/outputs.pyi
vsstubs/_template/plugin.pyi
vsstubs/_template/props.pyi
vs_stubs-1.0.0.dist-info/METADATA
vs_stubs-1.0.0.dist-info/WHEEL
vs_stubs-1.0.0.dist-info/entry_points.txt
vs_stubs-1.0.0.dist-info/licenses/LICENSE
vs_stubs-1.0.0.dist-info/RECORD
