Metadata-Version: 2.4
Name: vs-stubs
Version: 1.0.0
Summary: Typing stubs for VapourSynth
Project-URL: Homepage, https://github.com/Ichunjo/vs-stubs
Project-URL: Repository, https://github.com/Ichunjo/vs-stubs
Project-URL: Issues, https://github.com/Ichunjo/vs-stubs/issues
Author-email: Vardë <ichunjo.le.terrible@gmail.com>
License: MIT
License-File: LICENSE
Keywords: python,stubs,typing
Classifier: Development Status :: 5 - Production/Stable
Classifier: Intended Audience :: Developers
Classifier: License :: OSI Approved :: MIT License
Classifier: Operating System :: OS Independent
Classifier: Programming Language :: Python :: 3
Classifier: Programming Language :: Python :: 3.13
Classifier: Topic :: Software Development :: Code Generators
Classifier: Topic :: Software Development :: Libraries
Classifier: Topic :: Utilities
Classifier: Typing :: Typed
Requires-Python: >=3.13
Requires-Dist: typer[all]
Requires-Dist: vapoursynth>=73
